jupyter_cogram/__init__.py
jupyter_cogram/__main__.py
jupyter_cogram/jupyter_cogram.yaml
jupyter_cogram/main.js
jupyter_cogram/etc/jupyter-cogram-extension.json
jupyter_cogram/jupyter_cogram_serverextension/__init__.py
jupyter_cogram-0.11.23.data/data/etc/jupyter/jupyter_notebook_config.d/jupyter-cogram-extension.json
jupyter_cogram-0.11.23.data/data/share/jupyter/nbextensions/jupyter-cogram/__init__.py
jupyter_cogram-0.11.23.data/data/share/jupyter/nbextensions/jupyter-cogram/__main__.py
jupyter_cogram-0.11.23.data/data/share/jupyter/nbextensions/jupyter-cogram/jupyter_cogram.yaml
jupyter_cogram-0.11.23.data/data/share/jupyter/nbextensions/jupyter-cogram/main.js
jupyter_cogram-0.11.23.data/data/share/jupyter/nbextensions/jupyter-cogram/jupyter_cogram_serverextension/__init__.py
jupyter_cogram-0.11.23.dist-info/METADATA
jupyter_cogram-0.11.23.dist-info/WHEEL
jupyter_cogram-0.11.23.dist-info/top_level.txt
jupyter_cogram-0.11.23.dist-info/RECORD
