Metadata-Version: 2.1
Name: jupyter-cogram
Version: 0.11.23
Summary: Intuitive coding for Jupyter Notebook using natural language.
Home-page: https://cogram.com
Author: ricwo
Author-email: rick@cogram.com
License: UNKNOWN
Keywords: machine learning,NLP,code generation,program synthesis
Platform: UNKNOWN
Classifier: Programming Language :: Python
Classifier: Programming Language :: Python :: 3
Classifier: Programming Language :: Python :: 3.6
Classifier: Programming Language :: Python :: 3.7
Classifier: Programming Language :: Python :: 3.8
Classifier: Development Status :: 4 - Beta
Classifier: Operating System :: MacOS
Classifier: Operating System :: Unix
Classifier: Operating System :: Microsoft :: Windows
Classifier: License :: Other/Proprietary License
Requires-Python: >=3.6
Requires-Dist: notebook (~=6.0)
Requires-Dist: requests (<3.0,>=2.0)
Requires-Dist: aiohttp (~=3.7.4.post0)
Requires-Dist: importlib-metadata (>=1.0) ; python_version < "3.8"
